{
    "$schema": "https://schemas.wp.org/trunk/block.json",
    "apiVersion": 3,
    "name": "event-core-blocks/features-item",
    "version": "0.1.0",
    "title": "Feature Item",
    "category": "layout",
    "parent": [ "event-core-blocks/features-grid" ],
    "icon": "saved",
    "description": "Отдельная карточка преимущества.",
    "attributes": {
        "title": {
            "type": "string",
            "source": "html",
            "selector": "h3"
        },
        "description": {
            "type": "string",
            "source": "html",
            "selector": "p"
        }
    },
    "supports": {
        "html": false,
        "reusable": false
    },
    "textdomain": "event-core-blocks",
    "editorScript": "file:./index.js"
}